AW9523B/AW9523B.py
AW9523B/__init__.py
aw9523b-1.1.1.dist-info/METADATA
aw9523b-1.1.1.dist-info/WHEEL
aw9523b-1.1.1.dist-info/top_level.txt
aw9523b-1.1.1.dist-info/RECORD
