Metadata-Version: 2.1
Name: aw9523b
Version: 1.1.1
Summary: a library for raspberry pi gpio extend using aw9523b
Home-page: UNKNOWN
Author: Jam Wu
Author-email: 312023299@qq.com
License: MIT License
Keywords: gpio extend
Platform: any
Classifier: Programming Language :: Python :: 3
Classifier: License :: OSI Approved :: MIT License
Requires-Python: >=3.4
Requires-Dist: Adafruit-GPIO
Requires-Dist: RPi.GPIO
